README.md
setup.py
pyprel/__init__.py
pyprel.egg-info/PKG-INFO
pyprel.egg-info/SOURCES.txt
pyprel.egg-info/dependency_links.txt
pyprel.egg-info/not-zip-safe
pyprel.egg-info/requires.txt
pyprel.egg-info/top_level.txt