Metadata-Version: 1.0
Name: pyprel
Version: 2018.9.14.1501
Summary: Python print elegant
Home-page: https://github.com/wdbm/pyprel
Author: Will Breaden Madden
Author-email: wbm@protonmail.ch
License: GPLv3
Platform: UNKNOWN
